{
  "building-delete": "Usuń",
  "building-move": "Przesuń",
  "contact_completed": "Kontrakt został wypełniony.",
  "contact_unlocked": "Nowy kontrakt został odblokowany.",
  "equipment_unknown": "Błąd: Nieznany ekwipunek.", 
  "equipment_type_unknown": "Błąd: Nieznany typ ekwipunku.", 
  "equipment_space_already_occupied": "Błąd: To miejsce zostało już zajęte.", 
  "equipment_missing_resources": "Błąd: Za mała ilość zasobów aby wyprodukować ten rodzaj ekwipunku.", 
  "market_exchange_no_enough_money": "Błąd: Za mało pieniędzy na tę transakcję.",
  "market_exchange_no_enough_resource": "Błąd: Za mało zasobów na tę transakcję.", 
  "market_exchange_no_enough_space": "Błąd: Za mało miejsca na tę transakcję.",
  "popup-close": "Zamknij",
  "loading-game": "Ładowanie gry...",
  "money-format": "%amount%$",
  "resource-buy": "Kup (%price%$)",
  "resource-sell": "Sprzedaj (%price%$)",
  "work-in-progress": "W trakcie tworzenia",
  "delete-building-message": "Czy chciałbyś usunąć to wyposażenie?", 
  "delete-building-info": "Otrzymasz 75% oryginalnej ceny.",
  "yes": "Tak",
  "no": "Nie",
  "please_update": "Proszę zaktualizować grę, a następnie ją zrestartować."
}